station_simulator
