Metadata-Version: 1.1
Name: station-simulator
Version: 0.1.0
Summary: Tool for generating station CSV data
Home-page: https://github.com/asascience-open/station-simulator/
Author: Luke Campbell
Author-email: luke.campbell@rpsgroup.com
License: UNKNOWN
Platform: UNKNOWN
Classifier: Development Status :: 2 - Pre-Alpha
Classifier: Intended Audience :: Developers
Classifier: Intended Audience :: Science/Research
Classifier: License :: OSI Approved :: MIT License
Classifier: Operating System :: POSIX
Classifier: Programming Language :: Python
Classifier: Programming Language :: Python :: 2.7
Classifier: Programming Language :: Python :: 3.5
Classifier: Topic :: Scientific/Engineering
